napari_caphid/__init__.py
napari_caphid/_reader.py
napari_caphid/_widget.py
napari_caphid/_writer.py
napari_caphid/napari.yaml
napari_caphid/utils.py
napari_caphid/_tests/__init__.py
napari_caphid/_tests/test_reader.py
napari_caphid/_tests/test_widget.py
napari_caphid/_tests/test_writer.py
napari_caphid-0.0.1.dist-info/LICENSE
napari_caphid-0.0.1.dist-info/METADATA
napari_caphid-0.0.1.dist-info/WHEEL
napari_caphid-0.0.1.dist-info/entry_points.txt
napari_caphid-0.0.1.dist-info/top_level.txt
napari_caphid-0.0.1.dist-info/RECORD
