Metadata-Version: 2.1
Name: napari-caphid
Version: 0.0.1
Summary: Annotation of aphid and update table
Home-page: https://github.com/hereariim/napari-caphid
Author: Herearii Metuarea
Author-email: herearii.metuarea@gmail.com
License: BSD-3-Clause
Project-URL: Bug Tracker, https://github.com/hereariim/napari-caphid/issues
Project-URL: Documentation, https://github.com/hereariim/napari-caphid#README.md
Project-URL: Source Code, https://github.com/hereariim/napari-caphid
Project-URL: User Support, https://github.com/hereariim/napari-caphid/issues
Classifier: Development Status :: 2 - Pre-Alpha
Classifier: Framework :: napari
Classifier: Intended Audience :: Developers
Classifier: License :: OSI Approved :: BSD License
Classifier: Operating System :: OS Independent
Classifier: Programming Language :: Python
Classifier: Programming Language :: Python :: 3
Classifier: Programming Language :: Python :: 3 :: Only
Classifier: Programming Language :: Python :: 3.8
Classifier: Programming Language :: Python :: 3.9
Classifier: Programming Language :: Python :: 3.10
Classifier: Topic :: Scientific/Engineering :: Image Processing
Requires-Python: >=3.8
License-File: LICENSE
Requires-Dist: numpy
Requires-Dist: magicgui
Requires-Dist: qtpy
Requires-Dist: opencv-python
Requires-Dist: tqdm
Requires-Dist: pandas
Requires-Dist: Pillow
Provides-Extra: testing
Requires-Dist: tox ; extra == 'testing'
Requires-Dist: pytest ; extra == 'testing'
Requires-Dist: pytest-cov ; extra == 'testing'
Requires-Dist: pytest-qt ; extra == 'testing'
Requires-Dist: napari ; extra == 'testing'
Requires-Dist: pyqt5 ; extra == 'testing'
